emailmessage/__init__.py
emailmessage/mail.py
emailmessage-0.2.1.dist-info/METADATA
emailmessage-0.2.1.dist-info/WHEEL
emailmessage-0.2.1.dist-info/top_level.txt
emailmessage-0.2.1.dist-info/RECORD
