Metadata-Version: 2.1
Name: emailmessage
Version: 0.2.1
Summary: test setup tools and my basical functions.
Home-page: https://github.com/Wolf-Warriors-FDU/mail_message
Author: Jiang Feng
Author-email: jiangf21@m.fudan.edu.cn
